[
  {
    "company": "Anduril",
    "title": "Electrical Engineering Intern",
    "location": "Costa Mesa, California, United States",
    "url": "https://job-boards.greenhouse.io/andurilindustries/jobs/4802466007?gh_jid=4802466007",
    "date_found": "2026-05-01",
    "disciplines": [
      "Templates : Intern"
    ]
  },
  {
    "company": "Anduril",
    "title": "Firmware Engineer Intern",
    "location": "Costa Mesa, California, United States",
    "url": "https://job-boards.greenhouse.io/andurilindustries/jobs/5121683007?gh_jid=5121683007",
    "date_found": "2026-05-01",
    "disciplines": [
      "Hardware Engineering : Electrical Engineering : Firmware"
    ]
  },
  {
    "company": "Anduril",
    "title": "Product Design Intern",
    "location": "Costa Mesa, California, United States",
    "url": "https://job-boards.greenhouse.io/andurilindustries/jobs/4830567007?gh_jid=4830567007",
    "date_found": "2026-05-01",
    "disciplines": [
      "Corporate Operations : COO Office : COO Office"
    ]
  },
  {
    "company": "Boeing",
    "title": "Back-End Developer Intern",
    "location": "KOR - Seoul, South Korea",
    "url": "https://boeing.wd1.myworkdayjobs.com/en-US/EXTERNAL_CAREERS/job/KOR---Seoul-South-Korea/Back-End-Developer-Intern_JR2026506058-2",
    "date_found": "2026-05-01",
    "disciplines": []
  },
  {
    "company": "Boeing",
    "title": "Intern - Boeing Japan Tokyo Office Intern- Tokyo, Japan",
    "location": "JPN - Tokyo, Japan",
    "url": "https://boeing.wd1.myworkdayjobs.com/en-US/EXTERNAL_CAREERS/job/JPN---Tokyo-Japan/Intern---Boeing-Japan-Tokyo-Office-Intern--Tokyo--Japan_JR2026505802-1",
    "date_found": "2026-05-01",
    "disciplines": []
  },
  {
    "company": "Boeing",
    "title": "Intern - Student Engineer",
    "location": "UKR - Kyiv, Ukraine",
    "url": "https://boeing.wd1.myworkdayjobs.com/en-US/EXTERNAL_CAREERS/job/UKR---Kyiv-Ukraine/Intern---Student-Engineer_JR2026499659-1",
    "date_found": "2026-05-01",
    "disciplines": []
  },
  {
    "company": "Boeing",
    "title": "Intern - Student Engineer - Nagoya, Japan",
    "location": "JPN - Nagoya, Japan",
    "url": "https://boeing.wd1.myworkdayjobs.com/en-US/EXTERNAL_CAREERS/job/JPN---Nagoya-Japan/Intern---Student-Engineer---Nagoya--Japan_JR2026506912-1",
    "date_found": "2026-05-01",
    "disciplines": []
  },
  {
    "company": "Boeing",
    "title": "Intern - Supply Chain Operation Intern - Nagoya/Tokyo, Japan",
    "location": "2 Locations",
    "url": "https://boeing.wd1.myworkdayjobs.com/en-US/EXTERNAL_CAREERS/job/JPN---Nagoya-Japan/Job-Posting-Title-Intern---Supply-Chain-Operation-Intern---Nagoya-Tokyo--Japan_JR2026507586-1",
    "date_found": "2026-05-01",
    "disciplines": []
  },
  {
    "company": "Boeing",
    "title": "UI/UX Development Intern",
    "location": "KOR - Seoul, South Korea",
    "url": "https://boeing.wd1.myworkdayjobs.com/en-US/EXTERNAL_CAREERS/job/KOR---Seoul-South-Korea/Front-End-Developer-Intern_JR2026506060-2",
    "date_found": "2026-05-01",
    "disciplines": []
  },
  {
    "company": "Booz Allen Hamilton",
    "title": "AI Data Analyst Intern",
    "location": "Lexington, MA",
    "url": "https://bah.wd1.myworkdayjobs.com/BAH_Jobs/job/Lexington-MA/AI-Data-Analyst-Intern_R0237476",
    "date_found": "2026-05-02",
    "disciplines": []
  },
  {
    "company": "Booz Allen Hamilton",
    "title": "AIOps Engineer Intern",
    "location": "Lexington, MA",
    "url": "https://bah.wd1.myworkdayjobs.com/BAH_Jobs/job/Lexington-MA/AIOps-Engineer-Intern_R0237477",
    "date_found": "2026-05-02",
    "disciplines": []
  },
  {
    "company": "Booz Allen Hamilton",
    "title": "Aerospace Engineer Intern",
    "location": "Huntsville, AL",
    "url": "https://bah.wd1.myworkdayjobs.com/BAH_Jobs/job/Huntsville-AL/Aerospace-Engineer-Intern_R0238291",
    "date_found": "2026-05-02",
    "disciplines": []
  },
  {
    "company": "Booz Allen Hamilton",
    "title": "Cyber Intern",
    "location": "San Antonio, TX",
    "url": "https://bah.wd1.myworkdayjobs.com/BAH_Jobs/job/San-Antonio-TX/Cyber-Intern_R0237140",
    "date_found": "2026-05-02",
    "disciplines": []
  },
  {
    "company": "Booz Allen Hamilton",
    "title": "Cyber Intern",
    "location": "San Antonio, TX",
    "url": "https://bah.wd1.myworkdayjobs.com/BAH_Jobs/job/San-Antonio-TX/Cyber-Intern_R0237150",
    "date_found": "2026-05-02",
    "disciplines": []
  },
  {
    "company": "Booz Allen Hamilton",
    "title": "Human Resources Intern",
    "location": "McLean, VA",
    "url": "https://bah.wd1.myworkdayjobs.com/BAH_Jobs/job/McLean-VA/Human-Resources-Intern_R0237793",
    "date_found": "2026-05-02",
    "disciplines": []
  },
  {
    "company": "Booz Allen Hamilton",
    "title": "Human Resources Intern",
    "location": "McLean, VA",
    "url": "https://bah.wd1.myworkdayjobs.com/BAH_Jobs/job/McLean-VA/Human-Resources-Intern_R0237923-1",
    "date_found": "2026-05-02",
    "disciplines": []
  },
  {
    "company": "Booz Allen Hamilton",
    "title": "Information Systems Intern",
    "location": "McLean, VA",
    "url": "https://bah.wd1.myworkdayjobs.com/BAH_Jobs/job/McLean-VA/Information-Systems-Intern_R0238499",
    "date_found": "2026-05-02",
    "disciplines": []
  },
  {
    "company": "Booz Allen Hamilton",
    "title": "Records Management Intern",
    "location": "Arlington, VA",
    "url": "https://bah.wd1.myworkdayjobs.com/BAH_Jobs/job/Arlington-VA/Records-Management-Intern_R0238759",
    "date_found": "2026-05-02",
    "disciplines": []
  },
  {
    "company": "Booz Allen Hamilton",
    "title": "Systems Administrator Intern",
    "location": "Annapolis Junction, MD",
    "url": "https://bah.wd1.myworkdayjobs.com/BAH_Jobs/job/Annapolis-Junction-MD/Systems-Administrator-Intern_R0237149",
    "date_found": "2026-05-02",
    "disciplines": []
  },
  {
    "company": "Booz Allen Hamilton",
    "title": "Test Engineer Intern",
    "location": "Lexington Park, MD",
    "url": "https://bah.wd1.myworkdayjobs.com/BAH_Jobs/job/Lexington-Park-MD/Test-Engineer-Intern_R0238087",
    "date_found": "2026-05-02",
    "disciplines": []
  },
  {
    "company": "Booz Allen Hamilton",
    "title": "University - Applied AI Intern",
    "location": "Washington, DC",
    "url": "https://bah.wd1.myworkdayjobs.com/BAH_Jobs/job/Washington-DC/University---Applied-AI-Intern_R0236827",
    "date_found": "2026-05-02",
    "disciplines": []
  },
  {
    "company": "Booz Allen Hamilton",
    "title": "University, Applied AI Intern",
    "location": "Washington, DC",
    "url": "https://bah.wd1.myworkdayjobs.com/BAH_Jobs/job/Washington-DC/University--Applied-AI-Intern_R0236820",
    "date_found": "2026-05-02",
    "disciplines": []
  },
  {
    "company": "Booz Allen Hamilton",
    "title": "University, Applied AI Software Developer Intern",
    "location": "McLean, VA",
    "url": "https://bah.wd1.myworkdayjobs.com/BAH_Jobs/job/McLean-VA/University--Applied-AI-Software-Developer_R0236821",
    "date_found": "2026-05-02",
    "disciplines": []
  },
  {
    "company": "Booz Allen Hamilton",
    "title": "University, Data Engineering Intern",
    "location": "Crane, IN",
    "url": "https://bah.wd1.myworkdayjobs.com/BAH_Jobs/job/Crane-IN/University--Data-Engineering-Intern_R0234416",
    "date_found": "2026-05-02",
    "disciplines": []
  },
  {
    "company": "Booz Allen Hamilton",
    "title": "University, Data Engineering Intern",
    "location": "Crane, IN",
    "url": "https://bah.wd1.myworkdayjobs.com/BAH_Jobs/job/Crane-IN/University--Data-Engineering-Intern_R0238206",
    "date_found": "2026-05-02",
    "disciplines": []
  },
  {
    "company": "Leidos",
    "title": "AI Data Science Intern",
    "location": "Orlando, FL",
    "url": "https://leidos.wd5.myworkdayjobs.com/en-US/External/job/Orlando-FL/AI-Data-Science-Intern_R-00170158",
    "date_found": "2026-05-01",
    "disciplines": []
  },
  {
    "company": "Leidos",
    "title": "Business Development High School Intern",
    "location": "Reston, VA",
    "url": "https://leidos.wd5.myworkdayjobs.com/en-US/External/job/Reston-VA/Business-Development-High-School-Intern_R-00180737",
    "date_found": "2026-05-01",
    "disciplines": []
  },
  {
    "company": "Leidos",
    "title": "CAD Drafter Intern",
    "location": "Walled Lake, MI",
    "url": "https://leidos.wd5.myworkdayjobs.com/en-US/External/job/Walled-Lake-MI/CAD-Drafter-Intern_R-00182153",
    "date_found": "2026-05-01",
    "disciplines": []
  },
  {
    "company": "Leidos",
    "title": "Capture Management Intern",
    "location": "2 Locations",
    "url": "https://leidos.wd5.myworkdayjobs.com/en-US/External/job/Reston-VA/Capture-Management-Intern_R-00181735",
    "date_found": "2026-05-01",
    "disciplines": []
  },
  {
    "company": "Leidos",
    "title": "Computer Engineering Co-op",
    "location": "Bethesda, MD",
    "url": "https://leidos.wd5.myworkdayjobs.com/en-US/External/job/Bethesda-MD/Computer-Engineering-Co-op_R-00173303",
    "date_found": "2026-05-01",
    "disciplines": []
  },
  {
    "company": "Leidos",
    "title": "Content Strategist Intern",
    "location": "6314 Remote/Teleworker US",
    "url": "https://leidos.wd5.myworkdayjobs.com/en-US/External/job/6314-RemoteTeleworker-US/Content-Strategist-Intern_R-00179396",
    "date_found": "2026-05-01",
    "disciplines": []
  },
  {
    "company": "Leidos",
    "title": "Cybersecurity Platform Intern",
    "location": "6314 Remote/Teleworker US",
    "url": "https://leidos.wd5.myworkdayjobs.com/en-US/External/job/6314-RemoteTeleworker-US/Cybersecurity-Platform-Intern_R-00179999",
    "date_found": "2026-05-01",
    "disciplines": []
  },
  {
    "company": "Leidos",
    "title": "Data Engineer Intern",
    "location": "Fort Belvoir, VA",
    "url": "https://leidos.wd5.myworkdayjobs.com/en-US/External/job/Fort-Belvoir-VA/Data-Engineer-Intern_R-00180867",
    "date_found": "2026-05-01",
    "disciplines": []
  },
  {
    "company": "Leidos",
    "title": "Data Engineer Intern",
    "location": "Fort Belvoir, VA",
    "url": "https://leidos.wd5.myworkdayjobs.com/en-US/External/job/Fort-Belvoir-VA/Data-Engineer-Intern_R-00182075",
    "date_found": "2026-05-01",
    "disciplines": []
  },
  {
    "company": "Leidos",
    "title": "Electrical Engineer Intern",
    "location": "2 Locations",
    "url": "https://leidos.wd5.myworkdayjobs.com/en-US/External/job/Reston-VA/Electrical-Engineer-Intern_R-00181662",
    "date_found": "2026-05-01",
    "disciplines": []
  },
  {
    "company": "Leidos",
    "title": "Electrical Engineering Intern",
    "location": "Beavercreek, OH",
    "url": "https://leidos.wd5.myworkdayjobs.com/en-US/External/job/Beavercreek-OH/Electrical-Engineering-Intern_R-00181724",
    "date_found": "2026-05-01",
    "disciplines": []
  },
  {
    "company": "Leidos",
    "title": "Electrical Engineering Intern – Rapid Integration and Prototyping",
    "location": "Huntsville, AL",
    "url": "https://leidos.wd5.myworkdayjobs.com/en-US/External/job/Huntsville-AL/Electrical-Engineering-Intern---Rapid-Integration-and-Prototyping_R-00181356",
    "date_found": "2026-05-01",
    "disciplines": []
  },
  {
    "company": "Leidos",
    "title": "Engineering Intern – High School",
    "location": "Huntsville, AL",
    "url": "https://leidos.wd5.myworkdayjobs.com/en-US/External/job/Huntsville-AL/Engineering-Intern---High-School_R-00182018",
    "date_found": "2026-05-01",
    "disciplines": []
  },
  {
    "company": "Leidos",
    "title": "Engineering Intern – Modeling and Simulation",
    "location": "Huntsville, AL",
    "url": "https://leidos.wd5.myworkdayjobs.com/en-US/External/job/Huntsville-AL/Engineering-Intern---Modeling-and-Simulation_R-00181951-1",
    "date_found": "2026-05-01",
    "disciplines": []
  },
  {
    "company": "Leidos",
    "title": "Ethics & Business Integrity Intern",
    "location": "Reston, VA",
    "url": "https://leidos.wd5.myworkdayjobs.com/en-US/External/job/Reston-VA/Ethics---Business-Integrity-Intern_R-00181745-1",
    "date_found": "2026-05-01",
    "disciplines": []
  },
  {
    "company": "Leidos",
    "title": "Global Security Analyst Intern",
    "location": "Reston, VA",
    "url": "https://leidos.wd5.myworkdayjobs.com/en-US/External/job/Reston-VA/Global-Security-Analyst-Intern_R-00181958",
    "date_found": "2026-05-01",
    "disciplines": []
  },
  {
    "company": "Leidos",
    "title": "Marketing Intern",
    "location": "Farnborough, Hampshire, UK",
    "url": "https://leidos.wd5.myworkdayjobs.com/en-US/External/job/Farnborough-Hampshire-UK/Marketing-Intern_R-00181600",
    "date_found": "2026-05-01",
    "disciplines": []
  },
  {
    "company": "Leidos",
    "title": "Mechanical Design and Analysis Intern",
    "location": "Huntsville, AL",
    "url": "https://leidos.wd5.myworkdayjobs.com/en-US/External/job/Huntsville-AL/Mechanical-Design-and-Analysis-Intern_R-00181314",
    "date_found": "2026-05-01",
    "disciplines": []
  },
  {
    "company": "Leidos",
    "title": "Mechanical Engineer Intern",
    "location": "2 Locations",
    "url": "https://leidos.wd5.myworkdayjobs.com/en-US/External/job/Reston-VA/Mechanical-Engineer-Intern_R-00181668",
    "date_found": "2026-05-01",
    "disciplines": []
  },
  {
    "company": "Leidos",
    "title": "Mechanical Engineering Intern",
    "location": "Long Beach, MS",
    "url": "https://leidos.wd5.myworkdayjobs.com/en-US/External/job/Long-Beach-MS/Mechanical-Engineering-Intern_R-00181990",
    "date_found": "2026-05-01",
    "disciplines": []
  },
  {
    "company": "Leidos",
    "title": "Migration Execution Intern",
    "location": "6314 Remote/Teleworker US",
    "url": "https://leidos.wd5.myworkdayjobs.com/en-US/External/job/6314-RemoteTeleworker-US/Migration-Execution-Intern_R-00176399",
    "date_found": "2026-05-01",
    "disciplines": []
  },
  {
    "company": "Leidos",
    "title": "Program Coordination Intern",
    "location": "Orlando, FL",
    "url": "https://leidos.wd5.myworkdayjobs.com/en-US/External/job/Orlando-FL/Program-Coordination-Intern_R-00181532",
    "date_found": "2026-05-01",
    "disciplines": []
  },
  {
    "company": "Leidos",
    "title": "Quantum Information Science Intern",
    "location": "Huntsville, AL",
    "url": "https://leidos.wd5.myworkdayjobs.com/en-US/External/job/Huntsville-AL/Quantum-Information-Science-Intern_R-00181429",
    "date_found": "2026-05-01",
    "disciplines": []
  },
  {
    "company": "Leidos",
    "title": "ServiceNow Intern",
    "location": "6314 Remote/Teleworker US",
    "url": "https://leidos.wd5.myworkdayjobs.com/en-US/External/job/6314-RemoteTeleworker-US/ServiceNow-Intern_R-00181809",
    "date_found": "2026-05-01",
    "disciplines": []
  },
  {
    "company": "Leidos",
    "title": "Signal Processing Intern",
    "location": "San Diego, CA",
    "url": "https://leidos.wd5.myworkdayjobs.com/en-US/External/job/San-Diego-CA/Signal-Processing-Intern_R-00181765",
    "date_found": "2026-05-01",
    "disciplines": []
  },
  {
    "company": "Leidos",
    "title": "Software Developer Intern",
    "location": "Annapolis Junction, MD",
    "url": "https://leidos.wd5.myworkdayjobs.com/en-US/External/job/Annapolis-Junction-MD/Software-Developer-Intern_R-00181646",
    "date_found": "2026-05-01",
    "disciplines": []
  },
  {
    "company": "Leidos",
    "title": "Software Developer Intern",
    "location": "2 Locations",
    "url": "https://leidos.wd5.myworkdayjobs.com/en-US/External/job/Reston-VA/Software-Developer-Intern_R-00181656",
    "date_found": "2026-05-01",
    "disciplines": []
  },
  {
    "company": "Leidos",
    "title": "Software Engineer Intern",
    "location": "6314 Remote/Teleworker US",
    "url": "https://leidos.wd5.myworkdayjobs.com/en-US/External/job/6314-RemoteTeleworker-US/Software-Engineer-Intern_R-00180869",
    "date_found": "2026-05-01",
    "disciplines": []
  },
  {
    "company": "Leidos",
    "title": "​​Intern – Speech Processing / ASR for Low-Resource Languages​",
    "location": "6314 Remote/Teleworker US",
    "url": "https://leidos.wd5.myworkdayjobs.com/en-US/External/job/6314-RemoteTeleworker-US/XMLNAME---Intern---Speech-Processing---ASR-for-Low-Resource-Languages-_R-00181128",
    "date_found": "2026-05-01",
    "disciplines": []
  },
  {
    "company": "Northrop Grumman",
    "title": "2026 High School Technical Intern - Grand Sky ND",
    "location": "United States-North Dakota-Emerado",
    "url": "https://ngc.wd1.myworkdayjobs.com/Northrop_Grumman_External_Site/job/United-States-North-Dakota-Emerado/XMLNAME-2026-High-School-Technical-Intern---Grand-Sky-ND_R10231513",
    "date_found": "2026-05-02",
    "disciplines": []
  },
  {
    "company": "Palantir",
    "title": "Deployment Strategist, Internship - US Government",
    "location": "Honolulu, HI",
    "url": "https://jobs.lever.co/palantir/a49d4181-a289-435a-b581-7f5af0497c8e",
    "date_found": "2026-05-01",
    "disciplines": [
      "Echo"
    ]
  },
  {
    "company": "Palantir",
    "title": "Forward Deployed Software Engineer, Internship - France",
    "location": "New York, NY",
    "url": "https://jobs.lever.co/palantir/ac0dc094-2480-43c2-8495-26ade227ff4f",
    "date_found": "2026-05-01",
    "disciplines": [
      "Delta"
    ]
  },
  {
    "company": "Palantir",
    "title": "Forward Deployed Software Engineer, Internship - Poland",
    "location": "New York, NY",
    "url": "https://jobs.lever.co/palantir/d582cd84-14fd-4aa3-b413-15982d286bd9",
    "date_found": "2026-05-01",
    "disciplines": [
      "Delta"
    ]
  },
  {
    "company": "Palantir",
    "title": "Forward Deployed Software Engineer, Internship - US Government",
    "location": "Honolulu, HI",
    "url": "https://jobs.lever.co/palantir/315f695d-04d1-4a9a-848e-cb2bec7a997e",
    "date_found": "2026-05-01",
    "disciplines": [
      "Delta"
    ]
  },
  {
    "company": "Palantir",
    "title": "Software Engineer, Internship",
    "location": "London, United Kingdom",
    "url": "https://jobs.lever.co/palantir/76a60923-bb49-40f5-b061-7c7eb1299602",
    "date_found": "2026-05-01",
    "disciplines": [
      "Dev"
    ]
  },
  {
    "company": "Palantir",
    "title": "Software Engineer, Internship",
    "location": "New York, NY",
    "url": "https://jobs.lever.co/palantir/7d69cf8a-06fd-4f05-bd84-27149db29c4d",
    "date_found": "2026-05-01",
    "disciplines": [
      "Dev"
    ]
  },
  {
    "company": "Palantir",
    "title": "UK Meritocracy Fellowship",
    "location": "London, United Kingdom",
    "url": "https://jobs.lever.co/palantir/be19ad5e-e323-41c9-8a22-1b34668b1889",
    "date_found": "2026-05-01",
    "disciplines": [
      "Business Development"
    ]
  },
  {
    "company": "Palantir",
    "title": "Year at Palantir, Internship",
    "location": "New York, NY",
    "url": "https://jobs.lever.co/palantir/030ece08-c341-4959-bdfe-314e89b691ce",
    "date_found": "2026-05-01",
    "disciplines": [
      "Business Development"
    ]
  },
  {
    "company": "Palantir",
    "title": "Year at Palantir, Internship",
    "location": "Washington, D.C.",
    "url": "https://jobs.lever.co/palantir/9410b487-c6c0-4178-903c-3311ce6b1861",
    "date_found": "2026-05-01",
    "disciplines": [
      "Business Development"
    ]
  }
]
